mcp48xx.py
circuitpython_mcp48xx-1.0.1.dist-info/LICENSE
circuitpython_mcp48xx-1.0.1.dist-info/METADATA
circuitpython_mcp48xx-1.0.1.dist-info/WHEEL
circuitpython_mcp48xx-1.0.1.dist-info/top_level.txt
circuitpython_mcp48xx-1.0.1.dist-info/RECORD
