Metadata-Version: 2.1
Name: circuitpython-mcp48xx
Version: 1.0.1
Summary: CircuitPython library for the MCP4801, MCP4811, MCP4821, MCP4802, MCP4812, and MCP4822 digital to analog converters.
Author-email: Steffen Kreutz <brushmate@gmail.com>
License: MIT
Project-URL: Homepage, https://github.com/brushmate/CircuitPython_MCP48XX
Keywords: adafruit,blinka,circuitpython,micropython,mcp4801,mcp4811,mcp4821,mcp4802,mcp4812,mcp4822
Classifier: Intended Audience :: Developers
Classifier: Topic :: Software Development :: Libraries
Classifier: Topic :: Software Development :: Embedded Systems
Classifier: Topic :: System :: Hardware
Classifier: License :: OSI Approved :: MIT License
Classifier: Programming Language :: Python :: 3
License-File: LICENSE
Requires-Dist: Adafruit-Blinka
Requires-Dist: adafruit-circuitpython-busdevice
Provides-Extra: optional
